{
  "url": "https://en.wikipedia.org/wiki/Quercus_quangtriensis",
  "classification": [
    {
      "Kingdom": "Plantae"
    },
    {
      "Clade": "Tracheophytes"
    },
    {
      "Clade": "Angiosperms"
    },
    {
      "Clade": "Eudicots"
    },
    {
      "Clade": "Rosids"
    },
    {
      "Order": "Fagales"
    },
    {
      "Family": "Fagaceae"
    },
    {
      "Genus": "Quercus"
    },
    {
      "Subgenus": "Quercus subg. Cyclobalanopsis"
    },
    {
      "Species": "Q. quangtriensis"
    }
  ],
  "text": {
    "__SUMMARY__": "Quercus quangtriensis is the accepted name of a tree species in the Asian sub-genus of 'ring-cupped oaks' and the family Fagaceae; there are no known subspecies.This oak tree grows up to 25 m tall and has been recorded from Vietnam, where it may be called sồi Quảng Trị (after the name of that Province).",
    "References": "",
    "External links": " Data related to Quercus quangtriensis at Wikispecies\n Media related to Quercus at Wikimedia Commons"
  }
}