{
  "url": "https://en.wikipedia.org/wiki/Acacia_podalyriifolia",
  "classification": [
    {
      "Kingdom": "Plantae"
    },
    {
      "Clade": "Tracheophytes"
    },
    {
      "Clade": "Angiosperms"
    },
    {
      "Clade": "Eudicots"
    },
    {
      "Clade": "Rosids"
    },
    {
      "Order": "Fabales"
    },
    {
      "Family": "Fabaceae"
    },
    {
      "Clade": "Mimosoideae"
    },
    {
      "Genus": "Acacia"
    },
    {
      "Species": "A. podalyriifolia"
    }
  ],
  "text": {
    "__SUMMARY__": "Acacia podalyriifolia is a perennial tree which is fast-growing and widely cultivated.  It is native to Australia but is also naturalised in Malaysia, Africa, India and South America.  Its uses include environmental management and it is also used as an ornamental tree.  It is very closely related to Acacia uncifera.  It grows to about 5 m (16 feet) in height and about the same in total width. It blooms during winter.\n\nCommon names for it are Mount Morgan wattle and Queensland silver wattle.\n\n\n== References =="
  }
}