{
  "url": "https://en.wikipedia.org/wiki/Ceratozamia_vovidesii",
  "classification": [
    {
      "Kingdom": "Plantae"
    },
    {
      "Clade": "Tracheophytes"
    },
    {
      "Division": "Cycadophyta"
    },
    {
      "Class": "Cycadopsida"
    },
    {
      "Order": "Cycadales"
    },
    {
      "Family": "Zamiaceae"
    },
    {
      "Genus": "Ceratozamia"
    },
    {
      "Species": "C. vovidesii"
    }
  ],
  "text": {
    "__SUMMARY__": "Ceratozamia vovidesii is a species of cycad in the family Zamiaceae endemic to the Sierra Madre de Chiapas of Mexico.",
    "References": "Whitelock, Loran M. 2002. The Cycads. Portland: Timber Press. ISBN 0-88192-522-5",
    "External links": "*  Data related to Ceratozamia vovidesii at Wikispecies"
  }
}