{
  "url": "https://en.wikipedia.org/wiki/Zamia_onan-reyesii",
  "classification": [
    {
      "Kingdom": "Plantae"
    },
    {
      "Clade": "Tracheophytes"
    },
    {
      "Division": "Cycadophyta"
    },
    {
      "Class": "Cycadopsida"
    },
    {
      "Order": "Cycadales"
    },
    {
      "Family": "Zamiaceae"
    },
    {
      "Genus": "Zamia"
    },
    {
      "Species": "Z. onan-reyesii"
    }
  ],
  "text": {
    "__SUMMARY__": "Zamia onan-reyesii is a species of cycad in the family Zamiaceae endemic to Cortés Department, northern Honduras.",
    "References": "Whitelock, Loran M. 2002. The Cycads. Portland: Timber Press. ISBN 0-88192-522-5",
    "External links": " Data related to Zamia onan-reyesii at Wikispecies"
  }
}