{
  "url": "https://en.wikipedia.org/wiki/Zamia_hymenophyllidia",
  "classification": [
    {
      "Kingdom": "Plantae"
    },
    {
      "Clade": "Tracheophytes"
    },
    {
      "Division": "Cycadophyta"
    },
    {
      "Class": "Cycadopsida"
    },
    {
      "Order": "Cycadales"
    },
    {
      "Family": "Zamiaceae"
    },
    {
      "Genus": "Zamia"
    },
    {
      "Species": "Z. hymenophyllidia"
    }
  ],
  "text": {
    "__SUMMARY__": "Zamia hymenophyllidia is a species of plant in the family Zamiaceae. It is found in Colombia (Amazonas Department) and Peru (Loreto Region). In Peru, it is found in Maynas, Pebas, and Brilla Nueva. It is threatened by habitat loss.\n\n\n== References =="
  }
}