{
  "url": "https://en.wikipedia.org/wiki/Typhlops_loveridgei",
  "classification": [
    {
      "Kingdom": "Animalia"
    },
    {
      "Phylum": "Chordata"
    },
    {
      "Class": "Reptilia"
    },
    {
      "Order": "Squamata"
    },
    {
      "Suborder": "Serpentes"
    },
    {
      "Family": "Typhlopidae"
    },
    {
      "Genus": "Indotyphlops"
    },
    {
      "Species": "I. loveridgei"
    }
  ],
  "text": {
    "__SUMMARY__": "Loveridge's worm snake (Indotyphlops loveridgei) is a harmless blind snake species endemic to northern India.  No subspecies are currently recognized.",
    "Etymology": "The specific name, loveridgei, is in honor of British herpetologist Arthur Loveridge.",
    "Geographic range": "It is known only from the type specimen, the type locality for which is uncertain: \"probably from North India\", and likely from \"Ambala or the Kulu Valley\".",
    "See also": "List of typhlopid species and subspecies.\nTyphlopidae by common name.\nTyphlopidae by taxonomic synonyms.",
    "References": "",
    "Further reading": "",
    "External links": "Indotyphlops loveridgei at the Reptarium.cz Reptile Database. Accessed 31 August 2007."
  }
}