{
  "url": "https://en.wikipedia.org/wiki/Grevillea_irrasa",
  "classification": [
    {
      "Kingdom": "Plantae"
    },
    {
      "Clade": "Tracheophytes"
    },
    {
      "Clade": "Angiosperms"
    },
    {
      "Clade": "Eudicots"
    },
    {
      "Order": "Proteales"
    },
    {
      "Family": "Proteaceae"
    },
    {
      "Genus": "Grevillea"
    },
    {
      "Species": "G. irrasa"
    }
  ],
  "text": {
    "__SUMMARY__": "Grevillea irrasa is a  shrub species which is endemic to New South Wales in Australia.  It  has a spreading to erect habit, growing 1.5–3 metres high. Flowers appear between  August and January (late winter to mid summer) in its native range. These are red, apricot or pink.The species was first formally described by Australian botanist  Bob Makinson in 2000, his description published in Flora of Australia. Two subspecies are recognised:\n\nGrevillea irrasa subsp. didymochiton\nGrevillea irrasa subsp. irrasaGrevillea irrasa occurs in dry sclerophyll forest in the south-east of New South Wales.\n\n\n== References =="
  }
}