{
  "url": "https://en.wikipedia.org/wiki/Conus_trigonicus",
  "classification": [
    {
      "Kingdom": "Animalia"
    },
    {
      "Phylum": "Mollusca"
    },
    {
      "Class": "Gastropoda"
    },
    {
      "Clade": "Caenogastropoda"
    },
    {
      "Clade": "Hypsogastropoda"
    },
    {
      "Clade": "Neogastropoda"
    },
    {
      "Superfamily": "Conoidea"
    },
    {
      "Family": "Conidae"
    },
    {
      "Genus": "Conus"
    },
    {
      "Species": "C. trigonicus"
    }
  ],
  "text": {
    "__SUMMARY__": "Conus trigonicus is an extinct species of sea snail, a marine gastropod mollusk in the family Conidae, the cone snails, cone shells or cones.",
    "Description": "",
    "Distribution": "This marine species is only known as a fossil, endemic to New Zealand.",
    "References": "Maxwell, P.A. (2009). Cenozoic Mollusca. pp 232–254 in Gordon, D.P. (ed.) New Zealand inventory of biodiversity. Volume one. Kingdom Animalia: Radiata, Lophotrochozoa, Deuterostomia. Canterbury University Press, Christchurch.",
    "External links": "To World Register of Marine Species"
  }
}