{
  "url": "https://en.wikipedia.org/wiki/Banksia_conferta",
  "classification": [
    {
      "Kingdom": "Plantae"
    },
    {
      "(unranked)": "Angiosperms"
    },
    {
      "(unranked)": "Eudicots"
    },
    {
      "Order": "Proteales"
    },
    {
      "Family": "Proteaceae"
    },
    {
      "Genus": "Banksia"
    },
    {
      "Species": "B. conferta"
    }
  ],
  "text": {
    "__SUMMARY__": "Banksia conferta, the glasshouse banksia,) is a species of montane shrub or small tree in the plant genus Banksia. It occurs as distinct subspecies in two widely separated locations: B. conferta subsp. conferta in southern Queensland on the Lamington Plateau and further north in the Glass House Mountains; and B. conferta subsp. penicillata in New South Wales from Bowral to north of Lithgow.",
    "References": "George, Alex S. (1981). \"The Genus Banksia L.f. (Proteaceae)\". Nuytsia. 3 (3): 239–473.\nGeorge, Alex (1999). \"Banksia\".  In Wilson, Annette (ed.). Flora of Australia: Volume 17B: Proteaceae 3: Hakea to Dryandra. CSIRO Publishing / Australian Biological Resources Study. pp. 175–251. ISBN 0-643-06454-0.\nTaylor, Anne; Hopper, Stephen (1988). The Banksia Atlas (Australian Flora and Fauna Series Number 8). Canberra: Australian Government Publishing Service. ISBN 0-644-07124-9.",
    "External links": "\"Banksia conferta\". Flora of Australia Online. Department of the Environment and Heritage, Australian Government."
  }
}