{
  "url": "https://en.wikipedia.org/wiki/Schefflera_polyclada",
  "classification": [
    {
      "Kingdom": "Plantae"
    },
    {
      "Clade": "Tracheophytes"
    },
    {
      "Clade": "Angiosperms"
    },
    {
      "Clade": "Eudicots"
    },
    {
      "Clade": "Asterids"
    },
    {
      "Order": "Apiales"
    },
    {
      "Family": "Araliaceae"
    },
    {
      "Genus": "Schefflera"
    },
    {
      "Species": "S. polyclada"
    }
  ],
  "text": {
    "__SUMMARY__": "Schefflera polyclada is a plant species found in Papua New Guinea. It is an extant taxon.\n\n\n== References =="
  }
}