{
  "url": "https://en.wikipedia.org/wiki/East_African_little_collared_fruit_bat",
  "classification": [
    {
      "Kingdom": "Animalia"
    },
    {
      "Phylum": "Chordata"
    },
    {
      "Class": "Mammalia"
    },
    {
      "Order": "Chiroptera"
    },
    {
      "Family": "Pteropodidae"
    },
    {
      "Genus": "Myonycteris"
    },
    {
      "Species": "M. relicta"
    }
  ],
  "text": {
    "__SUMMARY__": "The East African little collared fruit bat (Myonycteris relicta) is a species of megabat in the family Pteropodidae. It is found in Kenya, Tanzania, and Zimbabwe. Its natural habitats are subtropical or tropical dry forests and moist savanna. It is threatened by habitat loss.\n\n\n== Sources =="
  }
}