{
  "url": "https://en.wikipedia.org/wiki/Round-eared_tube-nosed_fruit_bat",
  "classification": [
    {
      "Kingdom": "Animalia"
    },
    {
      "Phylum": "Chordata"
    },
    {
      "Class": "Mammalia"
    },
    {
      "Order": "Chiroptera"
    },
    {
      "Family": "Pteropodidae"
    },
    {
      "Genus": "Nyctimene"
    },
    {
      "Species": "N. cyclotis"
    }
  ],
  "text": {
    "__SUMMARY__": "The round-eared tube-nosed fruit bat (Nyctimene cyclotis) is a species of bat in the family Pteropodidae. It is possibly conspecific with Nyctimene certans, although the taxonomy remains unresolved. The possible synonymy of the species was investigated by Randolph L. Peterson in 1991, finding the species split into two distinct groups based on morphology.  It is found in West Papua and Mansuar Island in Indonesia.\n\n\n== Sources =="
  }
}