{
  "url": "https://en.wikipedia.org/wiki/Epidendrum_parkinsonianum",
  "classification": [
    {
      "Kingdom": "Plantae"
    },
    {
      "(unranked)": "Angiosperms"
    },
    {
      "(unranked)": "Monocots"
    },
    {
      "Order": "Asparagales"
    },
    {
      "Family": "Orchidaceae"
    },
    {
      "Subfamily": "Epidendroideae"
    },
    {
      "Tribe": "Epidendreae"
    },
    {
      "Subtribe": "Laeliinae"
    },
    {
      "Genus": "Coilostylis"
    },
    {
      "Species": "C. parkinsoniana"
    }
  ],
  "text": {
    "__SUMMARY__": "Coilostylis parkinsoniana (Parkinson's coilostylis), formerly Epidendrum parkinsonianum, is an epiphytic species of orchid in the genus Coilostylis, occurring in Mexico and Central America."
  }
}