{
  "url": "https://en.wikipedia.org/wiki/Galium_migrans",
  "classification": [
    {
      "Kingdom": "Plantae"
    },
    {
      "Clade": "Tracheophytes"
    },
    {
      "Clade": "Angiosperms"
    },
    {
      "Clade": "Eudicots"
    },
    {
      "Clade": "Asterids"
    },
    {
      "Order": "Gentianales"
    },
    {
      "Family": "Rubiaceae"
    },
    {
      "Genus": "Galium"
    },
    {
      "Species": "G. migrans"
    }
  ],
  "text": {
    "__SUMMARY__": "Galium migrans is a species of flowering plant in the family Rubiaceae. Following a revision of the genus Galium, the distribution of Gallium migrans is now believed to be restricted to South Australia. Plants in New South Wales that were formerly identified as this species are  currently identified as Galium leptogonium.",
    "Subspecies": "Three subspecies are recognized as of May 2014:\nGalium migrans subsp. inversum I.Thomps.\nGalium migrans subsp. migrans\nGalium migrans subsp. trichogynum I.Thomps.\n\n\n== References =="
  }
}