{
  "url": "https://en.wikipedia.org/wiki/Galium_stellatum",
  "classification": [
    {
      "Kingdom": "Plantae"
    },
    {
      "Clade": "Tracheophytes"
    },
    {
      "Clade": "Angiosperms"
    },
    {
      "Clade": "Eudicots"
    },
    {
      "Clade": "Asterids"
    },
    {
      "Order": "Gentianales"
    },
    {
      "Family": "Rubiaceae"
    },
    {
      "Genus": "Galium"
    },
    {
      "Species": "G. stellatum"
    }
  ],
  "text": {
    "__SUMMARY__": "Galium stellatum (starry bedstraw or desert bedstraw) is a species of plant in the family Rubiaceae. It is widespread across most of Arizona, and found also in Baja California, Baja California Sur, southeastern California (Inyo, San Bernardino, Riverside, Imperial and San Diego Counties),  Nevada (Clark, Nye and Lincoln Cos.), Utah (Washington County).",
    "References": "",
    "External links": "Calflora taxon report\nDesert Ecology of Tucson, Pima Community College, desert bedstraw\nCalphotos, University of California at Berkeley\nTom Chester, Borrego Desert Plants: desert bedstraw, Galium stellatum ssp. eremicum"
  }
}