{
  "url": "https://en.wikipedia.org/wiki/Euphorbia_kischenensis",
  "classification": [
    {
      "Kingdom": "Plantae"
    },
    {
      "Clade": "Tracheophytes"
    },
    {
      "Clade": "Angiosperms"
    },
    {
      "Clade": "Eudicots"
    },
    {
      "Clade": "Rosids"
    },
    {
      "Order": "Malpighiales"
    },
    {
      "Family": "Euphorbiaceae"
    },
    {
      "Genus": "Euphorbia"
    },
    {
      "Species": "E. kischenensis"
    }
  ],
  "text": {
    "__SUMMARY__": "Euphorbia kischenensis is a species of plant in the family Euphorbiaceae. It is endemic to Yemen.  Its natural habitats are subtropical or tropical dry forests and subtropical or tropical dry shrubland.\n\n\n== References =="
  }
}