{
  "url": "https://en.wikipedia.org/wiki/Penicillium_claviforme",
  "classification": [
    {
      "Kingdom": "Fungi"
    },
    {
      "Division": "Ascomycota"
    },
    {
      "Class": "Eurotiomycetes"
    },
    {
      "Order": "Eurotiales"
    },
    {
      "Family": "Trichocomaceae"
    },
    {
      "Genus": "Penicillium"
    },
    {
      "Species": "P. claviforme"
    }
  ],
  "text": {
    "__SUMMARY__": "Penicillium claviforme is a species of Penicillium within the phylum Ascomycota.\n\nIt is found within the subgenus Terverticillium.\nIt has a coremium-type morphology in the sexual structures, named for its resemblance to matchsticks.\nIt is also known as Penicillium vulpinum.Also known as synnema, meaning 'pillow', because of the closely appressed conidiophores.",
    "References": "Alexopolous, C.J.; Mims, Charles W.; Blackwell, M.;  et al. (2004). Introductory Mycology (4th ed.). Wiley. ISBN 0-471-52229-5.\nMoss, M. (2004). \"Penicillium claviforme — an Impressive mould with an M.C. Cooke Connection\". Mycologist. 18 (4): 143–4. doi:10.1017/S0269915X04004124."
  }
}